pcalibration/__init__.py
pcalibration/cvap.py
pcalibration/ivap.py
pcalibration/trainer.py
pcalibration/utils.py
pcalibration-0.1.2.dist-info/LICENSE
pcalibration-0.1.2.dist-info/WHEEL
pcalibration-0.1.2.dist-info/METADATA
pcalibration-0.1.2.dist-info/RECORD
