Metadata-Version: 2.1
Name: pcalibration
Version: 0.1.2
Summary: 
Author: nutorbit
Author-email: nutorbitx@gmail.com
Requires-Python: >=3.8,<4.0
Classifier: Programming Language :: Python :: 3
Classifier: Programming Language :: Python :: 3.8
Classifier: Programming Language :: Python :: 3.9
Classifier: Programming Language :: Python :: 3.10
Classifier: Programming Language :: Python :: 3.11
Requires-Dist: matplotlib (>=3.7.1,<4.0.0)
Requires-Dist: scikit-learn (>=1.2.1,<2.0.0)
